{"timestamp": "2026-05-28T21:29:27.536307", "endpoint": "INCOME_STATEMENT", "params": {"symbol": "TCBK"}, "data": {"symbol": "TCBK", "annualReports": [{"fiscalDateEnding": "2025-12-31", "reportedCurrency": "USD", "grossProfit": "404516000", "totalRevenue": "533308000", "costOfRevenue": "128792000", "costofGoodsAndServicesSold": "128792000", "operatingIncome": "169244000", "sellingGeneralAndAdministrative": "169703000", "researchAndDevelopment": "None", "operatingExpenses": "235357000", "investmentIncomeNet": "None", "netInterestIncome": "349335000", "interestIncome": "469064000", "interestExpense": "119729000", "nonInterestIncome": "None", "otherNonOperatingIncome": "None", "depreciation": "None", "depreciationAndAmortization": "13560000", "incomeBeforeTax": "166159000", "incomeTaxExpense": "44601000", "interestAndDebtExpense": "None", "netIncomeFromContinuingOperations": "121558000", "comprehensiveIncomeNetOfTax": "None", "ebit": "169244000", "ebitda": "182804000", "netIncome": "121558000"}, {"fiscalDateEnding": "2024-12-31", "reportedCurrency": "USD", "grossProfit": "382131000", "totalRevenue": "523967000", "costOfRevenue": "141836000", "costofGoodsAndServicesSold": "141836000", "operatingIncome": "155123000", "sellingGeneralAndAdministrative": "156992000", "researchAndDevelopment": "None", "operatingExpenses": "227027000", "investmentIncomeNet": "None", "netInterestIncome": "329912000", "interestIncome": "465116000", "interestExpense": "135204000", "nonInterestIncome": "None", "otherNonOperatingIncome": "None", "depreciation": "None", "depreciationAndAmortization": "16068000", "incomeBeforeTax": "155104000", "incomeTaxExpense": "40236000", "interestAndDebtExpense": "None", "netIncomeFromContinuingOperations": "114868000", "comprehensiveIncomeNetOfTax": "None", "ebit": "155104000", "ebitda": "171172000", "netIncome": "114868000"}, {"fiscalDateEnding": "2023-12-31", "reportedCurrency": "USD", "grossProfit": "387140000", "totalRevenue": "492807000", "costOfRevenue": "105667000", "costofGoodsAndServicesSold": "105667000", "operatingIncome": "160928000", "sellingGeneralAndAdministrative": "141071000", "researchAndDevelopment": "None", "operatingExpenses": "226235000", "investmentIncomeNet": "None", "netInterestIncome": "367721000", "interestIncome": "424195000", "interestExpense": "81677000", "nonInterestIncome": "None", "otherNonOperatingIncome": "None", "depreciation": "None", "depreciationAndAmortization": "18848000", "incomeBeforeTax": "160905000", "incomeTaxExpense": "43515000", "interestAndDebtExpense": "None", "netIncomeFromContinuingOperations": "127658000", "comprehensiveIncomeNetOfTax": "None", "ebit": "160905000", "ebitda": "179753000", "netIncome": "117390000"}, {"fiscalDateEnding": "2022-12-31", "reportedCurrency": "USD", "grossProfit": "384049000", "totalRevenue": "412048000", "costOfRevenue": "27999000", "costofGoodsAndServicesSold": "27999000", "operatingIncome": "173907000", "sellingGeneralAndAdministrative": "132994000", "researchAndDevelopment": "None", "operatingExpenses": "210142000", "investmentIncomeNet": "None", "netInterestIncome": "345143000", "interestIncome": "354672000", "interestExpense": "9529000", "nonInterestIncome": "None", "otherNonOperatingIncome": "None", "depreciation": "None", "depreciationAndAmortization": "18379000", "incomeBeforeTax": "173907000", "incomeTaxExpense": "48488000", "interestAndDebtExpense": "None", "netIncomeFromContinuingOperations": "125419000", "comprehensiveIncomeNetOfTax": "None", "ebit": "173907000", "ebitda": "192286000", "netIncome": "125419000"}, {"fiscalDateEnding": "2021-12-31", "reportedCurrency": "USD", "grossProfit": "336171000", "totalRevenue": "334904000", "costOfRevenue": "-1267000", "costofGoodsAndServicesSold": "-1267000", "operatingIncome": "163703000", "sellingGeneralAndAdministrative": "108932000", "researchAndDevelopment": "None", "operatingExpenses": "172468000", "investmentIncomeNet": "None", "netInterestIncome": "270809000", "interestIncome": "276317000", "interestExpense": "5508000", "nonInterestIncome": "None", "otherNonOperatingIncome": "None", "depreciation": "None", "depreciationAndAmortization": "17279000", "incomeBeforeTax": "163703000", "incomeTaxExpense": "46048000", "interestAndDebtExpense": "None", "netIncomeFromContinuingOperations": "117655000", "comprehensiveIncomeNetOfTax": "None", "ebit": "163703000", "ebitda": "180982000", "netIncome": "117655000"}, {"fiscalDateEnding": "2020-12-31", "reportedCurrency": "USD", "grossProfit": "264909000", "totalRevenue": "317179000", "costOfRevenue": "52270000", "costofGoodsAndServicesSold": "52270000", "operatingIncome": "87350000", "sellingGeneralAndAdministrative": "113715000", "researchAndDevelopment": "None", "operatingExpenses": "177559000", "investmentIncomeNet": "None", "netInterestIncome": "256920000", "interestIncome": "266377000", "interestExpense": "9457000", "nonInterestIncome": "None", "otherNonOperatingIncome": "None", "depreciation": "None", "depreciationAndAmortization": "17570000", "incomeBeforeTax": "87350000", "incomeTaxExpense": "22536000", "interestAndDebtExpense": "None", "netIncomeFromContinuingOperations": "109886000", "comprehensiveIncomeNetOfTax": "None", "ebit": "87417000", "ebitda": "104987000", "netIncome": "64814000"}, {"fiscalDateEnding": "2019-12-31", "reportedCurrency": "USD", "grossProfit": "307078000", "totalRevenue": "320763000", "costOfRevenue": "13685000", "costofGoodsAndServicesSold": "13685000", "operatingIncome": "126822000", "sellingGeneralAndAdministrative": "107253000", "researchAndDevelopment": "None", "operatingExpenses": "180256000", "investmentIncomeNet": "None", "netInterestIncome": "255784000", "interestIncome": "271159000", "interestExpense": "15375000", "nonInterestIncome": "None", "otherNonOperatingIncome": "None", "depreciation": "None", "depreciationAndAmortization": "17230000", "incomeBeforeTax": "126822000", "incomeTaxExpense": "34750000", "interestAndDebtExpense": "None", "netIncomeFromContinuingOperations": "161572000", "comprehensiveIncomeNetOfTax": "None", "ebit": "126904000", "ebitda": "144134000", "netIncome": "92072000"}, {"fiscalDateEnding": "2018-12-31", "reportedCurrency": "USD", "grossProfit": "256961000", "totalRevenue": "272416000", "costOfRevenue": "15455000", "costofGoodsAndServicesSold": "15455000", "operatingIncome": "93352000", "sellingGeneralAndAdministrative": "95848000", "researchAndDevelopment": "0", "operatingExpenses": "163609000", "investmentIncomeNet": "None", "netInterestIncome": "213641000", "interestIncome": "226513000", "interestExpense": "12872000", "nonInterestIncome": "None", "otherNonOperatingIncome": "None", "depreciation": "None", "depreciationAndAmortization": "10513000", "incomeBeforeTax": "93352000", "incomeTaxExpense": "25032000", "interestAndDebtExpense": "None", "netIncomeFromContinuingOperations": "68320000", "comprehensiveIncomeNetOfTax": "None", "ebit": "93352000", "ebitda": "103865000", "netIncome": "68320000"}, {"fiscalDateEnding": "2017-12-31", "reportedCurrency": "USD", "grossProfit": "219926000", "totalRevenue": "226813000", "costOfRevenue": "6887000", "costofGoodsAndServicesSold": "6887000", "operatingIncome": "77512000", "sellingGeneralAndAdministrative": "84606000", "researchAndDevelopment": "0", "operatingExpenses": "142414000", "investmentIncomeNet": "None", "netInterestIncome": "173280000", "interestIncome": "180078000", "interestExpense": "6798000", "nonInterestIncome": "None", "otherNonOperatingIncome": "None", "depreciation": "None", "depreciationAndAmortization": "8176000", "incomeBeforeTax": "77512000", "incomeTaxExpense": "36958000", "interestAndDebtExpense": "None", "netIncomeFromContinuingOperations": "40554000", "comprehensiveIncomeNetOfTax": "None", "ebit": "77654000", "ebitda": "85830000", "netIncome": "40554000"}, {"fiscalDateEnding": "2016-12-31", "reportedCurrency": "USD", "grossProfit": "213521000", "totalRevenue": "213272000", "costOfRevenue": "-249000", "costofGoodsAndServicesSold": "-249000", "operatingIncome": "72523000", "sellingGeneralAndAdministrative": "82830000", "researchAndDevelopment": "0", "operatingExpenses": "140998000", "investmentIncomeNet": "None", "netInterestIncome": "165806000", "interestIncome": "171527000", "interestExpense": "5721000", "nonInterestIncome": "None", "otherNonOperatingIncome": "None", "depreciation": "None", "depreciationAndAmortization": "7851000", "incomeBeforeTax": "72523000", "incomeTaxExpense": "27712000", "interestAndDebtExpense": "None", "netIncomeFromContinuingOperations": "44811000", "comprehensiveIncomeNetOfTax": "None", "ebit": "72523000", "ebitda": "80374000", "netIncome": "44811000"}, {"fiscalDateEnding": "2015-12-31", "reportedCurrency": "USD", "grossProfit": "199365000", "totalRevenue": "202571000", "costOfRevenue": "3206000", "costofGoodsAndServicesSold": "3206000", "operatingIncome": "72714000", "sellingGeneralAndAdministrative": "73977000", "researchAndDevelopment": "0", "operatingExpenses": "126651000", "investmentIncomeNet": "None", "netInterestIncome": "155998000", "interestIncome": "161414000", "interestExpense": "5416000", "nonInterestIncome": "None", "otherNonOperatingIncome": "None", "depreciation": "None", "depreciationAndAmortization": "7063000", "incomeBeforeTax": "72714000", "incomeTaxExpense": "28896000", "interestAndDebtExpense": "None", "netIncomeFromContinuingOperations": "43818000", "comprehensiveIncomeNetOfTax": "None", "ebit": "72714000", "ebitda": "79777000", "netIncome": "43818000"}, {"fiscalDateEnding": "2014-12-31", "reportedCurrency": "USD", "grossProfit": "151999000", "totalRevenue": "152635000", "costOfRevenue": "636000", "costofGoodsAndServicesSold": "636000", "operatingIncome": "44616000", "sellingGeneralAndAdministrative": "59651000", "researchAndDevelopment": "0", "operatingExpenses": "107383000", "investmentIncomeNet": "None", "netInterestIncome": "None", "interestIncome": "None", "interestExpense": "4681000", "nonInterestIncome": "None", "otherNonOperatingIncome": "None", "depreciation": "None", "depreciationAndAmortization": "6181000", "incomeBeforeTax": "44616000", "incomeTaxExpense": "18508000", "interestAndDebtExpense": "None", "netIncomeFromContinuingOperations": "26108000", "comprehensiveIncomeNetOfTax": "None", "ebit": "44616000", "ebitda": "50797000", "netIncome": "26108000"}, {"fiscalDateEnding": "2013-12-31", "reportedCurrency": "USD", "grossProfit": "136928000", "totalRevenue": "140909000", "costOfRevenue": "3981000", "costofGoodsAndServicesSold": "3981000", "operatingIncome": "45804000", "sellingGeneralAndAdministrative": "54184000", "researchAndDevelopment": "0", "operatingExpenses": "91124000", "investmentIncomeNet": "None", "netInterestIncome": "None", "interestIncome": "None", "interestExpense": "4696000", "nonInterestIncome": "None", "otherNonOperatingIncome": "None", "depreciation": "None", "depreciationAndAmortization": "4832000", "incomeBeforeTax": "45804000", "incomeTaxExpense": "18405000", "interestAndDebtExpense": "None", "netIncomeFromContinuingOperations": "27399000", "comprehensiveIncomeNetOfTax": "None", "ebit": "45804000", "ebitda": "50636000", "netIncome": "27399000"}, {"fiscalDateEnding": "2012-12-31", "reportedCurrency": "USD", "grossProfit": "127539000", "totalRevenue": "144306000", "costOfRevenue": "16767000", "costofGoodsAndServicesSold": "16767000", "operatingIncome": "31931000", "sellingGeneralAndAdministrative": "52345000", "researchAndDevelopment": "0", "operatingExpenses": "95608000", "investmentIncomeNet": "None", "netInterestIncome": "None", "interestIncome": "None", "interestExpense": "7344000", "nonInterestIncome": "None", "otherNonOperatingIncome": "None", "depreciation": "None", "depreciationAndAmortization": "4501000", "incomeBeforeTax": "31931000", "incomeTaxExpense": "12937000", "interestAndDebtExpense": "None", "netIncomeFromContinuingOperations": "18994000", "comprehensiveIncomeNetOfTax": "None", "ebit": "31931000", "ebitda": "36432000", "netIncome": "18994000"}, {"fiscalDateEnding": "2011-12-31", "reportedCurrency": "USD", "grossProfit": "102983000", "totalRevenue": "136281000", "costOfRevenue": "33298000", "costofGoodsAndServicesSold": "33298000", "operatingIncome": "29782000", "sellingGeneralAndAdministrative": "46694000", "researchAndDevelopment": "0", "operatingExpenses": "73201000", "investmentIncomeNet": "None", "netInterestIncome": "None", "interestIncome": "None", "interestExpense": "10238000", "nonInterestIncome": "None", "otherNonOperatingIncome": "None", "depreciation": "None", "depreciationAndAmortization": "3486000", "incomeBeforeTax": "29782000", "incomeTaxExpense": "11192000", "interestAndDebtExpense": "None", "netIncomeFromContinuingOperations": "18590000", "comprehensiveIncomeNetOfTax": "None", "ebit": "29797000", "ebitda": "33283000", "netIncome": "18590000"}, {"fiscalDateEnding": "2010-12-31", "reportedCurrency": "USD", "grossProfit": "85676000", "totalRevenue": "137267000", "costOfRevenue": "51591000", "costofGoodsAndServicesSold": "51591000", "operatingIncome": "8471000", "sellingGeneralAndAdministrative": "40105000", "researchAndDevelopment": "None", "operatingExpenses": "77205000", "investmentIncomeNet": "None", "netInterestIncome": "None", "interestIncome": "None", "interestExpense": "14133000", "nonInterestIncome": "None", "otherNonOperatingIncome": "None", "depreciation": "None", "depreciationAndAmortization": "3799000", "incomeBeforeTax": "8471000", "incomeTaxExpense": "2466000", "interestAndDebtExpense": "None", "netIncomeFromContinuingOperations": "None", "comprehensiveIncomeNetOfTax": "None", "ebit": "8471000", "ebitda": "12270000", "netIncome": "6005000"}, {"fiscalDateEnding": "2009-12-31", "reportedCurrency": "USD", "grossProfit": "90597000", "totalRevenue": "142662000", "costOfRevenue": "52065000", "costofGoodsAndServicesSold": "52065000", "operatingIncome": "15147000", "sellingGeneralAndAdministrative": "39810000", "researchAndDevelopment": "None", "operatingExpenses": "75450000", "investmentIncomeNet": "None", "netInterestIncome": "None", "interestIncome": "None", "interestExpense": "20615000", "nonInterestIncome": "None", "otherNonOperatingIncome": "None", "depreciation": "None", "depreciationAndAmortization": "3753000", "incomeBeforeTax": "15147000", "incomeTaxExpense": "5185000", "interestAndDebtExpense": "None", "netIncomeFromContinuingOperations": "None", "comprehensiveIncomeNetOfTax": "None", "ebit": "15147000", "ebitda": "18900000", "netIncome": "9962000"}, {"fiscalDateEnding": "2008-12-31", "reportedCurrency": "USD", "grossProfit": "95697000", "totalRevenue": "148199000", "costOfRevenue": "52502000", "costofGoodsAndServicesSold": "52502000", "operatingIncome": "26959000", "sellingGeneralAndAdministrative": "38112000", "researchAndDevelopment": "None", "operatingExpenses": "68738000", "investmentIncomeNet": "None", "netInterestIncome": "None", "interestIncome": "None", "interestExpense": "31552000", "nonInterestIncome": "None", "otherNonOperatingIncome": "None", "depreciation": "None", "depreciationAndAmortization": "3956000", "incomeBeforeTax": "26959000", "incomeTaxExpense": "10161000", "interestAndDebtExpense": "None", "netIncomeFromContinuingOperations": "None", "comprehensiveIncomeNetOfTax": "None", "ebit": "26959000", "ebitda": "30915000", "netIncome": "16798000"}, {"fiscalDateEnding": "2007-12-31", "reportedCurrency": "USD", "grossProfit": "111244000", "totalRevenue": "154858000", "costOfRevenue": "43614000", "costofGoodsAndServicesSold": "43614000", "operatingIncome": "42338000", "sellingGeneralAndAdministrative": "38066000", "researchAndDevelopment": "None", "operatingExpenses": "68906000", "investmentIncomeNet": "None", "netInterestIncome": "None", "interestIncome": "None", "interestExpense": "40582000", "nonInterestIncome": "None", "otherNonOperatingIncome": "None", "depreciation": "None", "depreciationAndAmortization": "4856000", "incomeBeforeTax": "42338000", "incomeTaxExpense": "16645000", "interestAndDebtExpense": "None", "netIncomeFromContinuingOperations": "None", "comprehensiveIncomeNetOfTax": "None", "ebit": "42338000", "ebitda": "47194000", "netIncome": "25693000"}, {"fiscalDateEnding": "2006-12-31", "reportedCurrency": "USD", "grossProfit": "110844000", "totalRevenue": "146578000", "costOfRevenue": "35734000", "costofGoodsAndServicesSold": "35734000", "operatingIncome": "44118000", "sellingGeneralAndAdministrative": "36455000", "researchAndDevelopment": "None", "operatingExpenses": "66726000", "investmentIncomeNet": "None", "netInterestIncome": "None", "interestIncome": "None", "interestExpense": "34445000", "nonInterestIncome": "None", "otherNonOperatingIncome": "None", "depreciation": "None", "depreciationAndAmortization": "6003000", "incomeBeforeTax": "44118000", "incomeTaxExpense": "17288000", "interestAndDebtExpense": "None", "netIncomeFromContinuingOperations": "None", "comprehensiveIncomeNetOfTax": "None", "ebit": "44118000", "ebitda": "50121000", "netIncome": "26830000"}], "quarterlyReports": [{"fiscalDateEnding": "2026-03-31", "reportedCurrency": "USD", "grossProfit": "104948000", "totalRevenue": "134874000", "costOfRevenue": "29926000", "costofGoodsAndServicesSold": "29926000", "operatingIncome": "45881000", "sellingGeneralAndAdministrative": "41958000", "researchAndDevelopment": "None", "operatingExpenses": "59067000", "investmentIncomeNet": "None", "netInterestIncome": "90352000", "interestIncome": "116953000", "interestExpense": "26601000", "nonInterestIncome": "None", "otherNonOperatingIncome": "None", "depreciation": "None", "depreciationAndAmortization": "None", "incomeBeforeTax": "45881000", "incomeTaxExpense": "12196000", "interestAndDebtExpense": "None", "netIncomeFromContinuingOperations": "33685000", "comprehensiveIncomeNetOfTax": "None", "ebit": "None", "ebitda": "45881000", "netIncome": "33685000"}, {"fiscalDateEnding": "2025-12-31", "reportedCurrency": "USD", "grossProfit": "109395000", "totalRevenue": "137315000", "costOfRevenue": "27920000", "costofGoodsAndServicesSold": "27920000", "operatingIncome": "49576000", "sellingGeneralAndAdministrative": "50177000", "researchAndDevelopment": "None", "operatingExpenses": "59819000", "investmentIncomeNet": "None", "netInterestIncome": "91847000", "interestIncome": "119767000", "interestExpense": "27920000", "nonInterestIncome": "None", "otherNonOperatingIncome": "None", "depreciation": "None", "depreciationAndAmortization": "2966000", "incomeBeforeTax": "46576000", "incomeTaxExpense": "12942000", "interestAndDebtExpense": "None", "netIncomeFromContinuingOperations": "33634000", "comprehensiveIncomeNetOfTax": "None", "ebit": "49576000", "ebitda": "52542000", "netIncome": "33634000"}, {"fiscalDateEnding": "2025-09-30", "reportedCurrency": "USD", "grossProfit": "104981000", "totalRevenue": "136083000", "costOfRevenue": "31102000", "costofGoodsAndServicesSold": "31102000", "operatingIncome": "46468000", "sellingGeneralAndAdministrative": "39011000", "researchAndDevelopment": "None", "operatingExpenses": "58513000", "investmentIncomeNet": "None", "netInterestIncome": "89179000", "interestIncome": "119611000", "interestExpense": "30432000", "nonInterestIncome": "None", "otherNonOperatingIncome": "None", "depreciation": "None", "depreciationAndAmortization": "3598000", "incomeBeforeTax": "46468000", "incomeTaxExpense": "12449000", "interestAndDebtExpense": "None", "netIncomeFromContinuingOperations": "34019000", "comprehensiveIncomeNetOfTax": "None", "ebit": "46468000", "ebitda": "50066000", "netIncome": "34019000"}, {"fiscalDateEnding": "2025-06-30", "reportedCurrency": "USD", "grossProfit": "97101000", "totalRevenue": "131608000", "costOfRevenue": "34507000", "costofGoodsAndServicesSold": "34507000", "operatingIncome": "37813000", "sellingGeneralAndAdministrative": "39583000", "researchAndDevelopment": "None", "operatingExpenses": "59288000", "investmentIncomeNet": "None", "netInterestIncome": "86146000", "interestIncome": "115988000", "interestExpense": "29842000", "nonInterestIncome": "None", "otherNonOperatingIncome": "None", "depreciation": "None", "depreciationAndAmortization": "3480000", "incomeBeforeTax": "37813000", "incomeTaxExpense": "10271000", "interestAndDebtExpense": "None", "netIncomeFromContinuingOperations": "27542000", "comprehensiveIncomeNetOfTax": "None", "ebit": "37813000", "ebitda": "41293000", "netIncome": "27542000"}, {"fiscalDateEnding": "2025-03-31", "reportedCurrency": "USD", "grossProfit": "93039000", "totalRevenue": "128302000", "costOfRevenue": "35263000", "costofGoodsAndServicesSold": "35263000", "operatingIncome": "35387000", "sellingGeneralAndAdministrative": "40932000", "researchAndDevelopment": "None", "operatingExpenses": "57737000", "investmentIncomeNet": "None", "netInterestIncome": "82163000", "interestIncome": "113698000", "interestExpense": "31535000", "nonInterestIncome": "None", "otherNonOperatingIncome": "None", "depreciation": "None", "depreciationAndAmortization": "3516000", "incomeBeforeTax": "35302000", "incomeTaxExpense": "8939000", "interestAndDebtExpense": "None", "netIncomeFromContinuingOperations": "26363000", "comprehensiveIncomeNetOfTax": "None", "ebit": "35302000", "ebitda": "38818000", "netIncome": "26363000"}, {"fiscalDateEnding": "2024-12-31", "reportedCurrency": "USD", "grossProfit": "96933000", "totalRevenue": "131387000", "costOfRevenue": "34454000", "costofGoodsAndServicesSold": "34454000", "operatingIncome": "38895000", "sellingGeneralAndAdministrative": "39532000", "researchAndDevelopment": "None", "operatingExpenses": "58045000", "investmentIncomeNet": "None", "netInterestIncome": "83711000", "interestIncome": "116463000", "interestExpense": "32752000", "nonInterestIncome": "None", "otherNonOperatingIncome": "None", "depreciation": "None", "depreciationAndAmortization": "3935000", "incomeBeforeTax": "38888000", "incomeTaxExpense": "9854000", "interestAndDebtExpense": "None", "netIncomeFromContinuingOperations": "29034000", "comprehensiveIncomeNetOfTax": "None", "ebit": "38888000", "ebitda": "42823000", "netIncome": "29034000"}, {"fiscalDateEnding": "2024-09-30", "reportedCurrency": "USD", "grossProfit": "97148000", "totalRevenue": "132104000", "costOfRevenue": "34956000", "costofGoodsAndServicesSold": "34956000", "operatingIncome": "39405000", "sellingGeneralAndAdministrative": "39741000", "researchAndDevelopment": "None", "operatingExpenses": "57749000", "investmentIncomeNet": "None", "netInterestIncome": "82235000", "interestIncome": "116971000", "interestExpense": "34736000", "nonInterestIncome": "None", "otherNonOperatingIncome": "None", "depreciation": "None", "depreciationAndAmortization": "4045000", "incomeBeforeTax": "39399000", "incomeTaxExpense": "10348000", "interestAndDebtExpense": "None", "netIncomeFromContinuingOperations": "29051000", "comprehensiveIncomeNetOfTax": "None", "ebit": "39399000", "ebitda": "43444000", "netIncome": "29051000"}, {"fiscalDateEnding": "2024-06-30", "reportedCurrency": "USD", "grossProfit": "95471000", "totalRevenue": "130911000", "costOfRevenue": "35440000", "costofGoodsAndServicesSold": "35440000", "operatingIncome": "39119000", "sellingGeneralAndAdministrative": "36545000", "researchAndDevelopment": "None", "operatingExpenses": "56352000", "investmentIncomeNet": "None", "netInterestIncome": "81610000", "interestIncome": "116645000", "interestExpense": "35035000", "nonInterestIncome": "None", "otherNonOperatingIncome": "None", "depreciation": "None", "depreciationAndAmortization": "4051000", "incomeBeforeTax": "39119000", "incomeTaxExpense": "10085000", "interestAndDebtExpense": "None", "netIncomeFromContinuingOperations": "29034000", "comprehensiveIncomeNetOfTax": "None", "ebit": "39119000", "ebitda": "43170000", "netIncome": "29034000"}, {"fiscalDateEnding": "2024-03-31", "reportedCurrency": "USD", "grossProfit": "92579000", "totalRevenue": "129565000", "costOfRevenue": "36986000", "costofGoodsAndServicesSold": "36986000", "operatingIncome": "37698000", "sellingGeneralAndAdministrative": "35555000", "researchAndDevelopment": "None", "operatingExpenses": "54881000", "investmentIncomeNet": "None", "netInterestIncome": "82356000", "interestIncome": "115037000", "interestExpense": "32681000", "nonInterestIncome": "None", "otherNonOperatingIncome": "None", "depreciation": "None", "depreciationAndAmortization": "4037000", "incomeBeforeTax": "37698000", "incomeTaxExpense": "9949000", "interestAndDebtExpense": "None", "netIncomeFromContinuingOperations": "27749000", "comprehensiveIncomeNetOfTax": "None", "ebit": "37708000", "ebitda": "41745000", "netIncome": "27749000"}, {"fiscalDateEnding": "2023-12-31", "reportedCurrency": "USD", "grossProfit": "94785000", "totalRevenue": "130067000", "costOfRevenue": "35282000", "costofGoodsAndServicesSold": "35282000", "operatingIncome": "36400000", "sellingGeneralAndAdministrative": "35352000", "researchAndDevelopment": "None", "operatingExpenses": "58385000", "investmentIncomeNet": "None", "netInterestIncome": "86258000", "interestIncome": "115550000", "interestExpense": "29292000", "nonInterestIncome": "None", "otherNonOperatingIncome": "None", "depreciation": "None", "depreciationAndAmortization": "4256000", "incomeBeforeTax": "36400000", "incomeTaxExpense": "10325000", "interestAndDebtExpense": "None", "netIncomeFromContinuingOperations": "26075000", "comprehensiveIncomeNetOfTax": "None", "ebit": "36400000", "ebitda": "40656000", "netIncome": "26075000"}, {"fiscalDateEnding": "2023-09-30", "reportedCurrency": "USD", "grossProfit": "98498000", "totalRevenue": "126910000", "costOfRevenue": "28412000", "costofGoodsAndServicesSold": "28412000", "operatingIncome": "42074000", "sellingGeneralAndAdministrative": "35657000", "researchAndDevelopment": "None", "operatingExpenses": "56424000", "investmentIncomeNet": "None", "netInterestIncome": "88123000", "interestIncome": "112380000", "interestExpense": "24257000", "nonInterestIncome": "None", "otherNonOperatingIncome": "None", "depreciation": "None", "depreciationAndAmortization": "4734000", "incomeBeforeTax": "42074000", "incomeTaxExpense": "11484000", "interestAndDebtExpense": "None", "netIncomeFromContinuingOperations": "30590000", "comprehensiveIncomeNetOfTax": "None", "ebit": "42074000", "ebitda": "46808000", "netIncome": "30590000"}, {"fiscalDateEnding": "2023-06-30", "reportedCurrency": "USD", "grossProfit": "92790000", "totalRevenue": "120997000", "costOfRevenue": "28207000", "costofGoodsAndServicesSold": "28207000", "operatingIncome": "33449000", "sellingGeneralAndAdministrative": "36707000", "researchAndDevelopment": "None", "operatingExpenses": "59341000", "investmentIncomeNet": "None", "netInterestIncome": "88601000", "interestIncome": "107158000", "interestExpense": "18557000", "nonInterestIncome": "None", "otherNonOperatingIncome": "None", "depreciation": "None", "depreciationAndAmortization": "4897000", "incomeBeforeTax": "33449000", "incomeTaxExpense": "8557000", "interestAndDebtExpense": "None", "netIncomeFromContinuingOperations": "24892000", "comprehensiveIncomeNetOfTax": "None", "ebit": "33449000", "ebitda": "38346000", "netIncome": "24892000"}, {"fiscalDateEnding": "2023-03-31", "reportedCurrency": "USD", "grossProfit": "101067000", "totalRevenue": "114833000", "costOfRevenue": "13766000", "costofGoodsAndServicesSold": "13766000", "operatingIncome": "48982000", "sellingGeneralAndAdministrative": "33355000", "researchAndDevelopment": "None", "operatingExpenses": "52085000", "investmentIncomeNet": "None", "netInterestIncome": "93336000", "interestIncome": "102907000", "interestExpense": "9571000", "nonInterestIncome": "None", "otherNonOperatingIncome": "None", "depreciation": "None", "depreciationAndAmortization": "4961000", "incomeBeforeTax": "48982000", "incomeTaxExpense": "13149000", "interestAndDebtExpense": "None", "netIncomeFromContinuingOperations": "35833000", "comprehensiveIncomeNetOfTax": "None", "ebit": "48982000", "ebitda": "53943000", "netIncome": "35833000"}, {"fiscalDateEnding": "2022-12-31", "reportedCurrency": "USD", "grossProfit": "108636000", "totalRevenue": "116970000", "costOfRevenue": "8334000", "costofGoodsAndServicesSold": "8334000", "operatingIncome": "51066000", "sellingGeneralAndAdministrative": "37426000", "researchAndDevelopment": "None", "operatingExpenses": "57570000", "investmentIncomeNet": "None", "netInterestIncome": "98900000", "interestIncome": "102989000", "interestExpense": "4089000", "nonInterestIncome": "None", "otherNonOperatingIncome": "None", "depreciation": "None", "depreciationAndAmortization": "4826000", "incomeBeforeTax": "51066000", "incomeTaxExpense": "14723000", "interestAndDebtExpense": "None", "netIncomeFromContinuingOperations": "36343000", "comprehensiveIncomeNetOfTax": "None", "ebit": "51066000", "ebitda": "55892000", "netIncome": "36343000"}, {"fiscalDateEnding": "2022-09-30", "reportedCurrency": "USD", "grossProfit": "104405000", "totalRevenue": "110460000", "costOfRevenue": "6055000", "costofGoodsAndServicesSold": "6055000", "operatingIncome": "51486000", "sellingGeneralAndAdministrative": "34356000", "researchAndDevelopment": "None", "operatingExpenses": "52919000", "investmentIncomeNet": "None", "netInterestIncome": "94106000", "interestIncome": "96366000", "interestExpense": "2260000", "nonInterestIncome": "None", "otherNonOperatingIncome": "None", "depreciation": "None", "depreciationAndAmortization": "4731000", "incomeBeforeTax": "51486000", "incomeTaxExpense": "14148000", "interestAndDebtExpense": "None", "netIncomeFromContinuingOperations": "37338000", "comprehensiveIncomeNetOfTax": "None", "ebit": "51486000", "ebitda": "56217000", "netIncome": "37338000"}, {"fiscalDateEnding": "2022-06-30", "reportedCurrency": "USD", "grossProfit": "97693000", "totalRevenue": "101702000", "costOfRevenue": "4009000", "costofGoodsAndServicesSold": "4009000", "operatingIncome": "43112000", "sellingGeneralAndAdministrative": "35149000", "researchAndDevelopment": "None", "operatingExpenses": "54581000", "investmentIncomeNet": "None", "netInterestIncome": "85046000", "interestIncome": "86955000", "interestExpense": "1909000", "nonInterestIncome": "None", "otherNonOperatingIncome": "None", "depreciation": "None", "depreciationAndAmortization": "4811000", "incomeBeforeTax": "43112000", "incomeTaxExpense": "11748000", "interestAndDebtExpense": "None", "netIncomeFromContinuingOperations": "31364000", "comprehensiveIncomeNetOfTax": "None", "ebit": "43112000", "ebitda": "47923000", "netIncome": "31364000"}, {"fiscalDateEnding": "2022-03-31", "reportedCurrency": "USD", "grossProfit": "73315000", "totalRevenue": "82916000", "costOfRevenue": "9601000", "costofGoodsAndServicesSold": "9601000", "operatingIncome": "28243000", "sellingGeneralAndAdministrative": "29317000", "researchAndDevelopment": "None", "operatingExpenses": "45072000", "investmentIncomeNet": "None", "netInterestIncome": "67924000", "interestIncome": "69195000", "interestExpense": "1271000", "nonInterestIncome": "None", "otherNonOperatingIncome": "None", "depreciation": "None", "depreciationAndAmortization": "4011000", "incomeBeforeTax": "28243000", "incomeTaxExpense": "7869000", "interestAndDebtExpense": "None", "netIncomeFromContinuingOperations": "20374000", "comprehensiveIncomeNetOfTax": "None", "ebit": "28243000", "ebitda": "32254000", "netIncome": "20374000"}, {"fiscalDateEnding": "2021-12-31", "reportedCurrency": "USD", "grossProfit": "83777000", "totalRevenue": "85998000", "costOfRevenue": "2221000", "costofGoodsAndServicesSold": "2221000", "operatingIncome": "38626000", "sellingGeneralAndAdministrative": "28344000", "researchAndDevelopment": "None", "operatingExpenses": "45151000", "investmentIncomeNet": "None", "netInterestIncome": "69783000", "interestIncome": "71024000", "interestExpense": "1241000", "nonInterestIncome": "None", "otherNonOperatingIncome": "None", "depreciation": "None", "depreciationAndAmortization": "4047000", "incomeBeforeTax": "38626000", "incomeTaxExpense": "10404000", "interestAndDebtExpense": "None", "netIncomeFromContinuingOperations": "28222000", "comprehensiveIncomeNetOfTax": "None", "ebit": "38626000", "ebitda": "42673000", "netIncome": "28222000"}, {"fiscalDateEnding": "2021-09-30", "reportedCurrency": "USD", "grossProfit": "83215000", "totalRevenue": "83175000", "costOfRevenue": "-40000", "costofGoodsAndServicesSold": "-40000", "operatingIncome": "38956000", "sellingGeneralAndAdministrative": "26947000", "researchAndDevelopment": "None", "operatingExpenses": "44259000", "investmentIncomeNet": "None", "netInterestIncome": "68233000", "interestIncome": "69628000", "interestExpense": "1395000", "nonInterestIncome": "None", "otherNonOperatingIncome": "None", "depreciation": "None", "depreciationAndAmortization": "4368000", "incomeBeforeTax": "38956000", "incomeTaxExpense": "11534000", "interestAndDebtExpense": "None", "netIncomeFromContinuingOperations": "27422000", "comprehensiveIncomeNetOfTax": "None", "ebit": "38937000", "ebitda": "43305000", "netIncome": "27422000"}, {"fiscalDateEnding": "2021-06-30", "reportedCurrency": "USD", "grossProfit": "81764000", "totalRevenue": "82900000", "costOfRevenue": "1136000", "costofGoodsAndServicesSold": "1136000", "operatingIncome": "39129000", "sellingGeneralAndAdministrative": "27699000", "researchAndDevelopment": "None", "operatingExpenses": "42635000", "investmentIncomeNet": "None", "netInterestIncome": "67083000", "interestIncome": "68479000", "interestExpense": "1396000", "nonInterestIncome": "None", "otherNonOperatingIncome": "None", "depreciation": "None", "depreciationAndAmortization": "4418000", "incomeBeforeTax": "39129000", "incomeTaxExpense": "10767000", "interestAndDebtExpense": "None", "netIncomeFromContinuingOperations": "28362000", "comprehensiveIncomeNetOfTax": "None", "ebit": "39129000", "ebitda": "43547000", "netIncome": "28362000"}, {"fiscalDateEnding": "2021-03-31", "reportedCurrency": "USD", "grossProfit": "87415000", "totalRevenue": "82831000", "costOfRevenue": "-4584000", "costofGoodsAndServicesSold": "-4584000", "operatingIncome": "46992000", "sellingGeneralAndAdministrative": "25942000", "researchAndDevelopment": "None", "operatingExpenses": "40423000", "investmentIncomeNet": "None", "netInterestIncome": "66440000", "interestIncome": "67916000", "interestExpense": "1476000", "nonInterestIncome": "None", "otherNonOperatingIncome": "None", "depreciation": "None", "depreciationAndAmortization": "4446000", "incomeBeforeTax": "46992000", "incomeTaxExpense": "13343000", "interestAndDebtExpense": "None", "netIncomeFromContinuingOperations": "33649000", "comprehensiveIncomeNetOfTax": "None", "ebit": "46992000", "ebitda": "51438000", "netIncome": "33649000"}, {"fiscalDateEnding": "2020-12-31", "reportedCurrency": "USD", "grossProfit": "76794000", "totalRevenue": "83303000", "costOfRevenue": "6509000", "costofGoodsAndServicesSold": "6509000", "operatingIncome": "32407000", "sellingGeneralAndAdministrative": "29074000", "researchAndDevelopment": "None", "operatingExpenses": "44387000", "investmentIncomeNet": "None", "netInterestIncome": "66422000", "interestIncome": "68081000", "interestExpense": "1659000", "nonInterestIncome": "None", "otherNonOperatingIncome": "None", "depreciation": "None", "depreciationAndAmortization": "4429000", "incomeBeforeTax": "32407000", "incomeTaxExpense": "8750000", "interestAndDebtExpense": "None", "netIncomeFromContinuingOperations": "68729000", "comprehensiveIncomeNetOfTax": "None", "ebit": "32407000", "ebitda": "36836000", "netIncome": "23657000"}, {"fiscalDateEnding": "2020-09-30", "reportedCurrency": "USD", "grossProfit": "69628000", "totalRevenue": "79261000", "costOfRevenue": "9633000", "costofGoodsAndServicesSold": "9633000", "operatingIncome": "24228000", "sellingGeneralAndAdministrative": "29859000", "researchAndDevelopment": "None", "operatingExpenses": "45400000", "investmentIncomeNet": "None", "netInterestIncome": "63231000", "interestIncome": "65215000", "interestExpense": "1984000", "nonInterestIncome": "None", "otherNonOperatingIncome": "None", "depreciation": "None", "depreciationAndAmortization": "4366000", "incomeBeforeTax": "24228000", "incomeTaxExpense": "6622000", "interestAndDebtExpense": "None", "netIncomeFromContinuingOperations": "17606000", "comprehensiveIncomeNetOfTax": "None", "ebit": "24228000", "ebitda": "28594000", "netIncome": "17606000"}, {"fiscalDateEnding": "2020-06-30", "reportedCurrency": "USD", "grossProfit": "52878000", "totalRevenue": "77611000", "costOfRevenue": "24733000", "costofGoodsAndServicesSold": "24733000", "operatingIncome": "8522000", "sellingGeneralAndAdministrative": "27415000", "researchAndDevelopment": "None", "operatingExpenses": "44356000", "investmentIncomeNet": "None", "netInterestIncome": "64436000", "interestIncome": "66925000", "interestExpense": "2489000", "nonInterestIncome": "None", "otherNonOperatingIncome": "None", "depreciation": "None", "depreciationAndAmortization": "4364000", "incomeBeforeTax": "8522000", "incomeTaxExpense": "1092000", "interestAndDebtExpense": "None", "netIncomeFromContinuingOperations": "7430000", "comprehensiveIncomeNetOfTax": "None", "ebit": "8537000", "ebitda": "12901000", "netIncome": "7430000"}, {"fiscalDateEnding": "2020-03-31", "reportedCurrency": "USD", "grossProfit": "65610000", "totalRevenue": "77005000", "costOfRevenue": "11395000", "costofGoodsAndServicesSold": "11395000", "operatingIncome": "22193000", "sellingGeneralAndAdministrative": "27367000", "researchAndDevelopment": "None", "operatingExpenses": "43417000", "investmentIncomeNet": "None", "netInterestIncome": "62831000", "interestIncome": "66156000", "interestExpense": "3325000", "nonInterestIncome": "None", "otherNonOperatingIncome": "None", "depreciation": "None", "depreciationAndAmortization": "4411000", "incomeBeforeTax": "22193000", "incomeTaxExpense": "6072000", "interestAndDebtExpense": "None", "netIncomeFromContinuingOperations": "16121000", "comprehensiveIncomeNetOfTax": "None", "ebit": "22193000", "ebitda": "26604000", "netIncome": "16121000"}, {"fiscalDateEnding": "2019-12-31", "reportedCurrency": "USD", "grossProfit": "77169000", "totalRevenue": "80593000", "costOfRevenue": "3424000", "costofGoodsAndServicesSold": "3424000", "operatingIncome": "31716000", "sellingGeneralAndAdministrative": "27412000", "researchAndDevelopment": "None", "operatingExpenses": "45453000", "investmentIncomeNet": "None", "netInterestIncome": "63884000", "interestIncome": "67606000", "interestExpense": "3722000", "nonInterestIncome": "None", "otherNonOperatingIncome": "None", "depreciation": "None", "depreciationAndAmortization": "8127000", "incomeBeforeTax": "31716000", "incomeTaxExpense": "8826000", "interestAndDebtExpense": "None", "netIncomeFromContinuingOperations": "92390000", "comprehensiveIncomeNetOfTax": "None", "ebit": "31716000", "ebitda": "39843000", "netIncome": "22890000"}, {"fiscalDateEnding": "2019-09-30", "reportedCurrency": "USD", "grossProfit": "77832000", "totalRevenue": "81704000", "costOfRevenue": "3872000", "costofGoodsAndServicesSold": "3872000", "operatingIncome": "32781000", "sellingGeneralAndAdministrative": "26993000", "researchAndDevelopment": "None", "operatingExpenses": "45051000", "investmentIncomeNet": "None", "netInterestIncome": "64380000", "interestIncome": "68581000", "interestExpense": "4201000", "nonInterestIncome": "None", "otherNonOperatingIncome": "None", "depreciation": "None", "depreciationAndAmortization": "333000", "incomeBeforeTax": "32781000", "incomeTaxExpense": "9386000", "interestAndDebtExpense": "None", "netIncomeFromContinuingOperations": "23395000", "comprehensiveIncomeNetOfTax": "None", "ebit": "32781000", "ebitda": "33114000", "netIncome": "23395000"}, {"fiscalDateEnding": "2019-06-30", "reportedCurrency": "USD", "grossProfit": "76030000", "totalRevenue": "80432000", "costOfRevenue": "4402000", "costofGoodsAndServicesSold": "4402000", "operatingIncome": "30504000", "sellingGeneralAndAdministrative": "27209000", "researchAndDevelopment": "None", "operatingExpenses": "45526000", "investmentIncomeNet": "None", "netInterestIncome": "64010000", "interestIncome": "67875000", "interestExpense": "3865000", "nonInterestIncome": "None", "otherNonOperatingIncome": "None", "depreciation": "None", "depreciationAndAmortization": "5021000", "incomeBeforeTax": "30504000", "incomeTaxExpense": "7443000", "interestAndDebtExpense": "None", "netIncomeFromContinuingOperations": "23061000", "comprehensiveIncomeNetOfTax": "None", "ebit": "30391000", "ebitda": "35412000", "netIncome": "23061000"}, {"fiscalDateEnding": "2019-03-31", "reportedCurrency": "USD", "grossProfit": "76049000", "totalRevenue": "78036000", "costOfRevenue": "1987000", "costofGoodsAndServicesSold": "1987000", "operatingIncome": "31821000", "sellingGeneralAndAdministrative": "25639000", "researchAndDevelopment": "None", "operatingExpenses": "44228000", "investmentIncomeNet": "None", "netInterestIncome": "63510000", "interestIncome": "67097000", "interestExpense": "3587000", "nonInterestIncome": "None", "otherNonOperatingIncome": "None", "depreciation": "None", "depreciationAndAmortization": "3749000", "incomeBeforeTax": "31821000", "incomeTaxExpense": "9095000", "interestAndDebtExpense": "None", "netIncomeFromContinuingOperations": "22726000", "comprehensiveIncomeNetOfTax": "None", "ebit": "31859000", "ebitda": "35608000", "netIncome": "22726000"}, {"fiscalDateEnding": "2018-12-31", "reportedCurrency": "USD", "grossProfit": "74417000", "totalRevenue": "79286000", "costOfRevenue": "4869000", "costofGoodsAndServicesSold": "4869000", "operatingIncome": "30545000", "sellingGeneralAndAdministrative": "25536000", "researchAndDevelopment": "0", "operatingExpenses": "43872000", "investmentIncomeNet": "None", "netInterestIncome": "None", "interestIncome": "None", "interestExpense": "4063000", "nonInterestIncome": "None", "otherNonOperatingIncome": "None", "depreciation": "None", "depreciationAndAmortization": "3531000", "incomeBeforeTax": "30545000", "incomeTaxExpense": "7334000", "interestAndDebtExpense": "None", "netIncomeFromContinuingOperations": "23211000", "comprehensiveIncomeNetOfTax": "None", "ebit": "30545000", "ebitda": "34076000", "netIncome": "23211000"}, {"fiscalDateEnding": "2018-09-30", "reportedCurrency": "USD", "grossProfit": "68979000", "totalRevenue": "75695000", "costOfRevenue": "6716000", "costofGoodsAndServicesSold": "6716000", "operatingIncome": "22646000", "sellingGeneralAndAdministrative": "26360000", "researchAndDevelopment": "0", "operatingExpenses": "46333000", "investmentIncomeNet": "None", "netInterestIncome": "None", "interestIncome": "None", "interestExpense": "4065000", "nonInterestIncome": "None", "otherNonOperatingIncome": "None", "depreciation": "None", "depreciationAndAmortization": "3075000", "incomeBeforeTax": "22646000", "incomeTaxExpense": "6476000", "interestAndDebtExpense": "None", "netIncomeFromContinuingOperations": "16170000", "comprehensiveIncomeNetOfTax": "None", "ebit": "22646000", "ebitda": "25721000", "netIncome": "16170000"}, {"fiscalDateEnding": "2018-06-30", "reportedCurrency": "USD", "grossProfit": "57244000", "totalRevenue": "59215000", "costOfRevenue": "1971000", "costofGoodsAndServicesSold": "1971000", "operatingIncome": "20811000", "sellingGeneralAndAdministrative": "21870000", "researchAndDevelopment": "0", "operatingExpenses": "36433000", "investmentIncomeNet": "None", "netInterestIncome": "None", "interestIncome": "None", "interestExpense": "2609000", "nonInterestIncome": "None", "otherNonOperatingIncome": "None", "depreciation": "None", "depreciationAndAmortization": "1955000", "incomeBeforeTax": "20811000", "incomeTaxExpense": "5782000", "interestAndDebtExpense": "None", "netIncomeFromContinuingOperations": "15029000", "comprehensiveIncomeNetOfTax": "None", "ebit": "20811000", "ebitda": "22766000", "netIncome": "15029000"}, {"fiscalDateEnding": "2018-03-31", "reportedCurrency": "USD", "grossProfit": "56286000", "totalRevenue": "58185000", "costOfRevenue": "1899000", "costofGoodsAndServicesSold": "1899000", "operatingIncome": "19350000", "sellingGeneralAndAdministrative": "22082000", "researchAndDevelopment": "0", "operatingExpenses": "36936000", "investmentIncomeNet": "None", "netInterestIncome": "None", "interestIncome": "None", "interestExpense": "2135000", "nonInterestIncome": "None", "otherNonOperatingIncome": "None", "depreciation": "None", "depreciationAndAmortization": "1952000", "incomeBeforeTax": "19350000", "incomeTaxExpense": "5440000", "interestAndDebtExpense": "None", "netIncomeFromContinuingOperations": "13910000", "comprehensiveIncomeNetOfTax": "None", "ebit": "19363000", "ebitda": "21315000", "netIncome": "13910000"}, {"fiscalDateEnding": "2017-12-31", "reportedCurrency": "USD", "grossProfit": "54495000", "totalRevenue": "58040000", "costOfRevenue": "3545000", "costofGoodsAndServicesSold": "3545000", "operatingIncome": "17818000", "sellingGeneralAndAdministrative": "21034000", "researchAndDevelopment": "0", "operatingExpenses": "36677000", "investmentIncomeNet": "None", "netInterestIncome": "None", "interestIncome": "None", "interestExpense": "1868000", "nonInterestIncome": "None", "otherNonOperatingIncome": "None", "depreciation": "None", "depreciationAndAmortization": "2037000", "incomeBeforeTax": "17818000", "incomeTaxExpense": "14829000", "interestAndDebtExpense": "None", "netIncomeFromContinuingOperations": "2989000", "comprehensiveIncomeNetOfTax": "None", "ebit": "17818000", "ebitda": "19855000", "netIncome": "2989000"}, {"fiscalDateEnding": "2017-09-30", "reportedCurrency": "USD", "grossProfit": "54824000", "totalRevenue": "57418000", "costOfRevenue": "2594000", "costofGoodsAndServicesSold": "2594000", "operatingIncome": "19027000", "sellingGeneralAndAdministrative": "21360000", "researchAndDevelopment": "0", "operatingExpenses": "35797000", "investmentIncomeNet": "None", "netInterestIncome": "None", "interestIncome": "None", "interestExpense": "1829000", "nonInterestIncome": "None", "otherNonOperatingIncome": "None", "depreciation": "None", "depreciationAndAmortization": "2141000", "incomeBeforeTax": "19027000", "incomeTaxExpense": "7130000", "interestAndDebtExpense": "None", "netIncomeFromContinuingOperations": "11897000", "comprehensiveIncomeNetOfTax": "None", "ebit": "19027000", "ebitda": "21168000", "netIncome": "11897000"}, {"fiscalDateEnding": "2017-06-30", "reportedCurrency": "USD", "grossProfit": "56065000", "totalRevenue": "56879000", "costOfRevenue": "814000", "costofGoodsAndServicesSold": "814000", "operatingIncome": "21236000", "sellingGeneralAndAdministrative": "20914000", "researchAndDevelopment": "0", "operatingExpenses": "34829000", "investmentIncomeNet": "None", "netInterestIncome": "None", "interestIncome": "None", "interestExpense": "1610000", "nonInterestIncome": "None", "otherNonOperatingIncome": "None", "depreciation": "None", "depreciationAndAmortization": "2035000", "incomeBeforeTax": "21236000", "incomeTaxExpense": "7647000", "interestAndDebtExpense": "None", "netIncomeFromContinuingOperations": "13589000", "comprehensiveIncomeNetOfTax": "None", "ebit": "21236000", "ebitda": "23271000", "netIncome": "13589000"}, {"fiscalDateEnding": "2017-03-31", "reportedCurrency": "USD", "grossProfit": "54400000", "totalRevenue": "54334000", "costOfRevenue": "-66000", "costofGoodsAndServicesSold": "-66000", "operatingIncome": "19431000", "sellingGeneralAndAdministrative": "21298000", "researchAndDevelopment": "0", "operatingExpenses": "34969000", "investmentIncomeNet": "None", "netInterestIncome": "None", "interestIncome": "None", "interestExpense": "1491000", "nonInterestIncome": "None", "otherNonOperatingIncome": "None", "depreciation": "None", "depreciationAndAmortization": "1963000", "incomeBeforeTax": "19431000", "incomeTaxExpense": "7352000", "interestAndDebtExpense": "None", "netIncomeFromContinuingOperations": "12079000", "comprehensiveIncomeNetOfTax": "None", "ebit": "19431000", "ebitda": "21394000", "netIncome": "12079000"}, {"fiscalDateEnding": "2016-12-31", "reportedCurrency": "USD", "grossProfit": "55192000", "totalRevenue": "55219000", "costOfRevenue": "27000", "costofGoodsAndServicesSold": "27000", "operatingIncome": "20487000", "sellingGeneralAndAdministrative": "20795000", "researchAndDevelopment": "0", "operatingExpenses": "34705000", "investmentIncomeNet": "None", "netInterestIncome": "None", "interestIncome": "None", "interestExpense": "1460000", "nonInterestIncome": "None", "otherNonOperatingIncome": "None", "depreciation": "None", "depreciationAndAmortization": "1964000", "incomeBeforeTax": "20487000", "incomeTaxExpense": "7954000", "interestAndDebtExpense": "None", "netIncomeFromContinuingOperations": "12533000", "comprehensiveIncomeNetOfTax": "None", "ebit": "20487000", "ebitda": "22451000", "netIncome": "12533000"}, {"fiscalDateEnding": "2016-09-30", "reportedCurrency": "USD", "grossProfit": "55394000", "totalRevenue": "52860000", "costOfRevenue": "-2534000", "costofGoodsAndServicesSold": "-2534000", "operatingIncome": "19893000", "sellingGeneralAndAdministrative": "21515000", "researchAndDevelopment": "0", "operatingExpenses": "35501000", "investmentIncomeNet": "None", "netInterestIncome": "None", "interestIncome": "None", "interestExpense": "1439000", "nonInterestIncome": "None", "otherNonOperatingIncome": "None", "depreciation": "None", "depreciationAndAmortization": "1984000", "incomeBeforeTax": "19893000", "incomeTaxExpense": "7694000", "interestAndDebtExpense": "None", "netIncomeFromContinuingOperations": "12199000", "comprehensiveIncomeNetOfTax": "None", "ebit": "19893000", "ebitda": "21877000", "netIncome": "12199000"}, {"fiscalDateEnding": "2016-06-30", "reportedCurrency": "USD", "grossProfit": "52176000", "totalRevenue": "52833000", "costOfRevenue": "657000", "costofGoodsAndServicesSold": "657000", "operatingIncome": "14911000", "sellingGeneralAndAdministrative": "20623000", "researchAndDevelopment": "0", "operatingExpenses": "37265000", "investmentIncomeNet": "None", "netInterestIncome": "None", "interestIncome": "None", "interestExpense": "1430000", "nonInterestIncome": "None", "otherNonOperatingIncome": "None", "depreciation": "None", "depreciationAndAmortization": "2078000", "incomeBeforeTax": "14911000", "incomeTaxExpense": "5506000", "interestAndDebtExpense": "None", "netIncomeFromContinuingOperations": "9405000", "comprehensiveIncomeNetOfTax": "None", "ebit": "14911000", "ebitda": "16989000", "netIncome": "9405000"}, {"fiscalDateEnding": "2016-03-31", "reportedCurrency": "USD", "grossProfit": "49754000", "totalRevenue": "51355000", "costOfRevenue": "1601000", "costofGoodsAndServicesSold": "1601000", "operatingIncome": "17232000", "sellingGeneralAndAdministrative": "19897000", "researchAndDevelopment": "0", "operatingExpenses": "32522000", "investmentIncomeNet": "None", "netInterestIncome": "None", "interestIncome": "None", "interestExpense": "1392000", "nonInterestIncome": "None", "otherNonOperatingIncome": "None", "depreciation": "None", "depreciationAndAmortization": "1825000", "incomeBeforeTax": "17232000", "incomeTaxExpense": "6558000", "interestAndDebtExpense": "None", "netIncomeFromContinuingOperations": "10674000", "comprehensiveIncomeNetOfTax": "None", "ebit": "17232000", "ebitda": "19057000", "netIncome": "10674000"}, {"fiscalDateEnding": "2015-12-31", "reportedCurrency": "USD", "grossProfit": "52635000", "totalRevenue": "53076000", "costOfRevenue": "441000", "costofGoodsAndServicesSold": "441000", "operatingIncome": "18810000", "sellingGeneralAndAdministrative": "19115000", "researchAndDevelopment": "0", "operatingExpenses": "33825000", "investmentIncomeNet": "None", "netInterestIncome": "None", "interestIncome": "None", "interestExpense": "1349000", "nonInterestIncome": "None", "otherNonOperatingIncome": "None", "depreciation": "None", "depreciationAndAmortization": "1709000", "incomeBeforeTax": "18810000", "incomeTaxExpense": "7388000", "interestAndDebtExpense": "None", "netIncomeFromContinuingOperations": "11422000", "comprehensiveIncomeNetOfTax": "None", "ebit": "18810000", "ebitda": "20519000", "netIncome": "11422000"}, {"fiscalDateEnding": "2015-09-30", "reportedCurrency": "USD", "grossProfit": "51744000", "totalRevenue": "52217000", "costOfRevenue": "473000", "costofGoodsAndServicesSold": "473000", "operatingIncome": "21062000", "sellingGeneralAndAdministrative": "18175000", "researchAndDevelopment": "0", "operatingExpenses": "30682000", "investmentIncomeNet": "None", "netInterestIncome": "None", "interestIncome": "None", "interestExpense": "1339000", "nonInterestIncome": "None", "otherNonOperatingIncome": "None", "depreciation": "None", "depreciationAndAmortization": "1686000", "incomeBeforeTax": "21062000", "incomeTaxExpense": "8368000", "interestAndDebtExpense": "None", "netIncomeFromContinuingOperations": "12694000", "comprehensiveIncomeNetOfTax": "None", "ebit": "21062000", "ebitda": "22748000", "netIncome": "12694000"}, {"fiscalDateEnding": "2015-06-30", "reportedCurrency": "USD", "grossProfit": "50249000", "totalRevenue": "50962000", "costOfRevenue": "713000", "costofGoodsAndServicesSold": "713000", "operatingIncome": "18798000", "sellingGeneralAndAdministrative": "17936000", "researchAndDevelopment": "0", "operatingExpenses": "31451000", "investmentIncomeNet": "None", "netInterestIncome": "None", "interestIncome": "None", "interestExpense": "1346000", "nonInterestIncome": "None", "otherNonOperatingIncome": "None", "depreciation": "None", "depreciationAndAmortization": "1885000", "incomeBeforeTax": "18798000", "incomeTaxExpense": "7432000", "interestAndDebtExpense": "None", "netIncomeFromContinuingOperations": "11366000", "comprehensiveIncomeNetOfTax": "None", "ebit": "18798000", "ebitda": "20683000", "netIncome": "11366000"}, {"fiscalDateEnding": "2015-03-31", "reportedCurrency": "USD", "grossProfit": "45556000", "totalRevenue": "47135000", "costOfRevenue": "1579000", "costofGoodsAndServicesSold": "1579000", "operatingIncome": "14044000", "sellingGeneralAndAdministrative": "18751000", "researchAndDevelopment": "0", "operatingExpenses": "31512000", "investmentIncomeNet": "None", "netInterestIncome": "None", "interestIncome": "None", "interestExpense": "1382000", "nonInterestIncome": "None", "otherNonOperatingIncome": "None", "depreciation": "None", "depreciationAndAmortization": "1783000", "incomeBeforeTax": "14044000", "incomeTaxExpense": "5708000", "interestAndDebtExpense": "None", "netIncomeFromContinuingOperations": "8336000", "comprehensiveIncomeNetOfTax": "None", "ebit": "14044000", "ebitda": "15827000", "netIncome": "8336000"}, {"fiscalDateEnding": "2014-12-31", "reportedCurrency": "USD", "grossProfit": "45160000", "totalRevenue": "45176000", "costOfRevenue": "16000", "costofGoodsAndServicesSold": "16000", "operatingIncome": "9580000", "sellingGeneralAndAdministrative": "18167000", "researchAndDevelopment": "0", "operatingExpenses": "35580000", "investmentIncomeNet": "None", "netInterestIncome": "None", "interestIncome": "None", "interestExpense": "1437000", "nonInterestIncome": "None", "otherNonOperatingIncome": "None", "depreciation": "None", "depreciationAndAmortization": "1989000", "incomeBeforeTax": "9580000", "incomeTaxExpense": "3930000", "interestAndDebtExpense": "None", "netIncomeFromContinuingOperations": "5650000", "comprehensiveIncomeNetOfTax": "None", "ebit": "9580000", "ebitda": "11569000", "netIncome": "5650000"}, {"fiscalDateEnding": "2014-09-30", "reportedCurrency": "USD", "grossProfit": "38958000", "totalRevenue": "37063000", "costOfRevenue": "-1895000", "costofGoodsAndServicesSold": "-1895000", "operatingIncome": "14235000", "sellingGeneralAndAdministrative": "13862000", "researchAndDevelopment": "0", "operatingExpenses": "24723000", "investmentIncomeNet": "None", "netInterestIncome": "None", "interestIncome": "None", "interestExpense": "1082000", "nonInterestIncome": "None", "otherNonOperatingIncome": "None", "depreciation": "None", "depreciationAndAmortization": "1384000", "incomeBeforeTax": "14235000", "incomeTaxExpense": "6001000", "interestAndDebtExpense": "None", "netIncomeFromContinuingOperations": "8234000", "comprehensiveIncomeNetOfTax": "None", "ebit": "14235000", "ebitda": "15619000", "netIncome": "8234000"}, {"fiscalDateEnding": "2014-06-30", "reportedCurrency": "USD", "grossProfit": "32802000", "totalRevenue": "35585000", "costOfRevenue": "2783000", "costofGoodsAndServicesSold": "2783000", "operatingIncome": "8396000", "sellingGeneralAndAdministrative": "13798000", "researchAndDevelopment": "0", "operatingExpenses": "24406000", "investmentIncomeNet": "None", "netInterestIncome": "None", "interestIncome": "None", "interestExpense": "1075000", "nonInterestIncome": "None", "otherNonOperatingIncome": "None", "depreciation": "None", "depreciationAndAmortization": "1293000", "incomeBeforeTax": "8396000", "incomeTaxExpense": "3537000", "interestAndDebtExpense": "None", "netIncomeFromContinuingOperations": "4859000", "comprehensiveIncomeNetOfTax": "None", "ebit": "8396000", "ebitda": "9689000", "netIncome": "4859000"}, {"fiscalDateEnding": "2014-03-31", "reportedCurrency": "USD", "grossProfit": "35079000", "totalRevenue": "34811000", "costOfRevenue": "-268000", "costofGoodsAndServicesSold": "-268000", "operatingIncome": "12405000", "sellingGeneralAndAdministrative": "13824000", "researchAndDevelopment": "0", "operatingExpenses": "22674000", "investmentIncomeNet": "None", "netInterestIncome": "None", "interestIncome": "None", "interestExpense": "1087000", "nonInterestIncome": "None", "otherNonOperatingIncome": "None", "depreciation": "None", "depreciationAndAmortization": "1515000", "incomeBeforeTax": "12405000", "incomeTaxExpense": "5040000", "interestAndDebtExpense": "None", "netIncomeFromContinuingOperations": "7365000", "comprehensiveIncomeNetOfTax": "None", "ebit": "12405000", "ebitda": "13920000", "netIncome": "7365000"}, {"fiscalDateEnding": "2013-12-31", "reportedCurrency": "USD", "grossProfit": "32841000", "totalRevenue": "34136000", "costOfRevenue": "1295000", "costofGoodsAndServicesSold": "1295000", "operatingIncome": "8642000", "sellingGeneralAndAdministrative": "13751000", "researchAndDevelopment": "0", "operatingExpenses": "24199000", "investmentIncomeNet": "None", "netInterestIncome": "None", "interestIncome": "None", "interestExpense": "1123000", "nonInterestIncome": "None", "otherNonOperatingIncome": "None", "depreciation": "None", "depreciationAndAmortization": "1446000", "incomeBeforeTax": "8642000", "incomeTaxExpense": "3406000", "interestAndDebtExpense": "None", "netIncomeFromContinuingOperations": "5236000", "comprehensiveIncomeNetOfTax": "None", "ebit": "8642000", "ebitda": "10088000", "netIncome": "5236000"}, {"fiscalDateEnding": "2013-09-30", "reportedCurrency": "USD", "grossProfit": "35261000", "totalRevenue": "36037000", "costOfRevenue": "776000", "costofGoodsAndServicesSold": "776000", "operatingIncome": "12271000", "sellingGeneralAndAdministrative": "13433000", "researchAndDevelopment": "0", "operatingExpenses": "22990000", "investmentIncomeNet": "None", "netInterestIncome": "None", "interestIncome": "None", "interestExpense": "1169000", "nonInterestIncome": "None", "otherNonOperatingIncome": "None", "depreciation": "None", "depreciationAndAmortization": "1319000", "incomeBeforeTax": "12271000", "incomeTaxExpense": "4910000", "interestAndDebtExpense": "None", "netIncomeFromContinuingOperations": "7361000", "comprehensiveIncomeNetOfTax": "None", "ebit": "12271000", "ebitda": "13590000", "netIncome": "7361000"}, {"fiscalDateEnding": "2013-06-30", "reportedCurrency": "USD", "grossProfit": "33427000", "totalRevenue": "35208000", "costOfRevenue": "1781000", "costofGoodsAndServicesSold": "1781000", "operatingIncome": "10597000", "sellingGeneralAndAdministrative": "13433000", "researchAndDevelopment": "0", "operatingExpenses": "22830000", "investmentIncomeNet": "None", "netInterestIncome": "None", "interestIncome": "None", "interestExpense": "1167000", "nonInterestIncome": "None", "otherNonOperatingIncome": "None", "depreciation": "None", "depreciationAndAmortization": "1033000", "incomeBeforeTax": "10597000", "incomeTaxExpense": "4272000", "interestAndDebtExpense": "None", "netIncomeFromContinuingOperations": "6325000", "comprehensiveIncomeNetOfTax": "None", "ebit": "10597000", "ebitda": "11630000", "netIncome": "6325000"}, {"fiscalDateEnding": "2013-03-31", "reportedCurrency": "USD", "grossProfit": "35399000", "totalRevenue": "35528000", "costOfRevenue": "129000", "costofGoodsAndServicesSold": "129000", "operatingIncome": "14294000", "sellingGeneralAndAdministrative": "13567000", "researchAndDevelopment": "0", "operatingExpenses": "21105000", "investmentIncomeNet": "None", "netInterestIncome": "None", "interestIncome": "None", "interestExpense": "1237000", "nonInterestIncome": "None", "otherNonOperatingIncome": "None", "depreciation": "None", "depreciationAndAmortization": "1034000", "incomeBeforeTax": "14294000", "incomeTaxExpense": "5817000", "interestAndDebtExpense": "None", "netIncomeFromContinuingOperations": "8477000", "comprehensiveIncomeNetOfTax": "None", "ebit": "14294000", "ebitda": "15328000", "netIncome": "8477000"}, {"fiscalDateEnding": "2012-12-31", "reportedCurrency": "USD", "grossProfit": "30868000", "totalRevenue": "33764000", "costOfRevenue": "2896000", "costofGoodsAndServicesSold": "2896000", "operatingIncome": "8132000", "sellingGeneralAndAdministrative": "14731000", "researchAndDevelopment": "0", "operatingExpenses": "22736000", "investmentIncomeNet": "None", "netInterestIncome": "None", "interestIncome": "None", "interestExpense": "1372000", "nonInterestIncome": "None", "otherNonOperatingIncome": "None", "depreciation": "None", "depreciationAndAmortization": "1123000", "incomeBeforeTax": "8132000", "incomeTaxExpense": "3410000", "interestAndDebtExpense": "None", "netIncomeFromContinuingOperations": "4722000", "comprehensiveIncomeNetOfTax": "None", "ebit": "8132000", "ebitda": "9255000", "netIncome": "4722000"}, {"fiscalDateEnding": "2012-09-30", "reportedCurrency": "USD", "grossProfit": "33697000", "totalRevenue": "36063000", "costOfRevenue": "2366000", "costofGoodsAndServicesSold": "2366000", "operatingIncome": "8636000", "sellingGeneralAndAdministrative": "12952000", "researchAndDevelopment": "0", "operatingExpenses": "25061000", "investmentIncomeNet": "None", "netInterestIncome": "None", "interestIncome": "None", "interestExpense": "1834000", "nonInterestIncome": "None", "otherNonOperatingIncome": "None", "depreciation": "None", "depreciationAndAmortization": "1146000", "incomeBeforeTax": "8636000", "incomeTaxExpense": "3616000", "interestAndDebtExpense": "None", "netIncomeFromContinuingOperations": "5020000", "comprehensiveIncomeNetOfTax": "None", "ebit": "8636000", "ebitda": "9782000", "netIncome": "5020000"}, {"fiscalDateEnding": "2012-06-30", "reportedCurrency": "USD", "grossProfit": "32608000", "totalRevenue": "37989000", "costOfRevenue": "5381000", "costofGoodsAndServicesSold": "5381000", "operatingIncome": "8773000", "sellingGeneralAndAdministrative": "13080000", "researchAndDevelopment": "0", "operatingExpenses": "23835000", "investmentIncomeNet": "None", "netInterestIncome": "None", "interestIncome": "None", "interestExpense": "2010000", "nonInterestIncome": "None", "otherNonOperatingIncome": "None", "depreciation": "None", "depreciationAndAmortization": "1161000", "incomeBeforeTax": "8773000", "incomeTaxExpense": "3452000", "interestAndDebtExpense": "None", "netIncomeFromContinuingOperations": "5321000", "comprehensiveIncomeNetOfTax": "None", "ebit": "8773000", "ebitda": "9934000", "netIncome": "5321000"}, {"fiscalDateEnding": "2012-03-31", "reportedCurrency": "USD", "grossProfit": "28738000", "totalRevenue": "34862000", "costOfRevenue": "6124000", "costofGoodsAndServicesSold": "6124000", "operatingIncome": "6390000", "sellingGeneralAndAdministrative": "13368000", "researchAndDevelopment": "0", "operatingExpenses": "22348000", "investmentIncomeNet": "None", "netInterestIncome": "None", "interestIncome": "None", "interestExpense": "2128000", "nonInterestIncome": "None", "otherNonOperatingIncome": "None", "depreciation": "None", "depreciationAndAmortization": "1071000", "incomeBeforeTax": "6390000", "incomeTaxExpense": "2459000", "interestAndDebtExpense": "None", "netIncomeFromContinuingOperations": "3931000", "comprehensiveIncomeNetOfTax": "None", "ebit": "6390000", "ebitda": "7461000", "netIncome": "3931000"}, {"fiscalDateEnding": "2011-12-31", "reportedCurrency": "USD", "grossProfit": "32340000", "totalRevenue": "40098000", "costOfRevenue": "7758000", "costofGoodsAndServicesSold": "7758000", "operatingIncome": "10264000", "sellingGeneralAndAdministrative": "10765000", "researchAndDevelopment": "0", "operatingExpenses": "22076000", "investmentIncomeNet": "None", "netInterestIncome": "None", "interestIncome": "None", "interestExpense": "2329000", "nonInterestIncome": "None", "otherNonOperatingIncome": "None", "depreciation": "None", "depreciationAndAmortization": "928000", "incomeBeforeTax": "10264000", "incomeTaxExpense": "3715000", "interestAndDebtExpense": "None", "netIncomeFromContinuingOperations": "0", "comprehensiveIncomeNetOfTax": "None", "ebit": "10264000", "ebitda": "11192000", "netIncome": "6549000"}, {"fiscalDateEnding": "2011-09-30", "reportedCurrency": "USD", "grossProfit": "31661000", "totalRevenue": "39195000", "costOfRevenue": "7534000", "costofGoodsAndServicesSold": "7534000", "operatingIncome": "10788000", "sellingGeneralAndAdministrative": "11930000", "researchAndDevelopment": "0", "operatingExpenses": "20873000", "investmentIncomeNet": "None", "netInterestIncome": "None", "interestIncome": "None", "interestExpense": "2465000", "nonInterestIncome": "None", "otherNonOperatingIncome": "None", "depreciation": "None", "depreciationAndAmortization": "841000", "incomeBeforeTax": "10788000", "incomeTaxExpense": "4318000", "interestAndDebtExpense": "None", "netIncomeFromContinuingOperations": "6470000", "comprehensiveIncomeNetOfTax": "None", "ebit": "10788000", "ebitda": "11629000", "netIncome": "6470000"}, {"fiscalDateEnding": "2011-06-30", "reportedCurrency": "USD", "grossProfit": "24443000", "totalRevenue": "32718000", "costOfRevenue": "8275000", "costofGoodsAndServicesSold": "8275000", "operatingIncome": "4348000", "sellingGeneralAndAdministrative": "10715000", "researchAndDevelopment": "0", "operatingExpenses": "20095000", "investmentIncomeNet": "None", "netInterestIncome": "None", "interestIncome": "None", "interestExpense": "2714000", "nonInterestIncome": "None", "otherNonOperatingIncome": "None", "depreciation": "None", "depreciationAndAmortization": "802000", "incomeBeforeTax": "4348000", "incomeTaxExpense": "1577000", "interestAndDebtExpense": "None", "netIncomeFromContinuingOperations": "2771000", "comprehensiveIncomeNetOfTax": "None", "ebit": "4348000", "ebitda": "5150000", "netIncome": "2771000"}, {"fiscalDateEnding": "2011-03-31", "reportedCurrency": "USD", "grossProfit": "24053000", "totalRevenue": "33784000", "costOfRevenue": "9731000", "costofGoodsAndServicesSold": "9731000", "operatingIncome": "4382000", "sellingGeneralAndAdministrative": "10793000", "researchAndDevelopment": "0", "operatingExpenses": "19671000", "investmentIncomeNet": "None", "netInterestIncome": "None", "interestIncome": "None", "interestExpense": "2730000", "nonInterestIncome": "None", "otherNonOperatingIncome": "None", "depreciation": "None", "depreciationAndAmortization": "915000", "incomeBeforeTax": "4382000", "incomeTaxExpense": "1582000", "interestAndDebtExpense": "None", "netIncomeFromContinuingOperations": "0", "comprehensiveIncomeNetOfTax": "None", "ebit": "4382000", "ebitda": "5297000", "netIncome": "2800000"}, {"fiscalDateEnding": "2010-12-31", "reportedCurrency": "USD", "grossProfit": "24328000", "totalRevenue": "35508000", "costOfRevenue": "11180000", "costofGoodsAndServicesSold": "11180000", "operatingIncome": "4858000", "sellingGeneralAndAdministrative": "10072000", "researchAndDevelopment": "0", "operatingExpenses": "19470000", "investmentIncomeNet": "None", "netInterestIncome": "None", "interestIncome": "None", "interestExpense": "3036000", "nonInterestIncome": "None", "otherNonOperatingIncome": "None", "depreciation": "None", "depreciationAndAmortization": "912000", "incomeBeforeTax": "4858000", "incomeTaxExpense": "1732000", "interestAndDebtExpense": "None", "netIncomeFromContinuingOperations": "0", "comprehensiveIncomeNetOfTax": "None", "ebit": "4858000", "ebitda": "5770000", "netIncome": "3126000"}, {"fiscalDateEnding": "2010-09-30", "reportedCurrency": "USD", "grossProfit": "20085000", "totalRevenue": "34396000", "costOfRevenue": "14311000", "costofGoodsAndServicesSold": "14311000", "operatingIncome": "-439000", "sellingGeneralAndAdministrative": "9898000", "researchAndDevelopment": "0", "operatingExpenses": "20524000", "investmentIncomeNet": "None", "netInterestIncome": "None", "interestIncome": "None", "interestExpense": "3497000", "nonInterestIncome": "None", "otherNonOperatingIncome": "None", "depreciation": "None", "depreciationAndAmortization": "940000", "incomeBeforeTax": "-439000", "incomeTaxExpense": "-440000", "interestAndDebtExpense": "None", "netIncomeFromContinuingOperations": "0", "comprehensiveIncomeNetOfTax": "None", "ebit": "-439000", "ebitda": "501000", "netIncome": "1000"}, {"fiscalDateEnding": "2010-06-30", "reportedCurrency": "USD", "grossProfit": "20238000", "totalRevenue": "33880000", "costOfRevenue": "13642000", "costofGoodsAndServicesSold": "13642000", "operatingIncome": "1830000", "sellingGeneralAndAdministrative": "9985000", "researchAndDevelopment": "0", "operatingExpenses": "18408000", "investmentIncomeNet": "None", "netInterestIncome": "None", "interestIncome": "None", "interestExpense": "3642000", "nonInterestIncome": "None", "otherNonOperatingIncome": "None", "depreciation": "None", "depreciationAndAmortization": "955000", "incomeBeforeTax": "1830000", "incomeTaxExpense": "510000", "interestAndDebtExpense": "None", "netIncomeFromContinuingOperations": "0", "comprehensiveIncomeNetOfTax": "None", "ebit": "1830000", "ebitda": "2785000", "netIncome": "1320000"}, {"fiscalDateEnding": "2010-03-31", "reportedCurrency": "USD", "grossProfit": "21025000", "totalRevenue": "33483000", "costOfRevenue": "12458000", "costofGoodsAndServicesSold": "12458000", "operatingIncome": "2222000", "sellingGeneralAndAdministrative": "10150000", "researchAndDevelopment": "0", "operatingExpenses": "18803000", "investmentIncomeNet": "None", "netInterestIncome": "None", "interestIncome": "None", "interestExpense": "3958000", "nonInterestIncome": "None", "otherNonOperatingIncome": "None", "depreciation": "None", "depreciationAndAmortization": "992000", "incomeBeforeTax": "2222000", "incomeTaxExpense": "664000", "interestAndDebtExpense": "None", "netIncomeFromContinuingOperations": "0", "comprehensiveIncomeNetOfTax": "None", "ebit": "2222000", "ebitda": "3214000", "netIncome": "1558000"}, {"fiscalDateEnding": "2009-12-31", "reportedCurrency": "USD", "grossProfit": "22594000", "totalRevenue": "35055000", "costOfRevenue": "12461000", "costofGoodsAndServicesSold": "12461000", "operatingIncome": "3066000", "sellingGeneralAndAdministrative": "9689000", "researchAndDevelopment": "0", "operatingExpenses": "19528000", "investmentIncomeNet": "None", "netInterestIncome": "None", "interestIncome": "None", "interestExpense": "4661000", "nonInterestIncome": "None", "otherNonOperatingIncome": "None", "depreciation": "None", "depreciationAndAmortization": "957000", "incomeBeforeTax": "3066000", "incomeTaxExpense": "753000", "interestAndDebtExpense": "None", "netIncomeFromContinuingOperations": "0", "comprehensiveIncomeNetOfTax": "None", "ebit": "3066000", "ebitda": "4023000", "netIncome": "2313000"}, {"fiscalDateEnding": "2009-09-30", "reportedCurrency": "USD", "grossProfit": "22898000", "totalRevenue": "35682000", "costOfRevenue": "12784000", "costofGoodsAndServicesSold": "12784000", "operatingIncome": "3521000", "sellingGeneralAndAdministrative": "10263000", "researchAndDevelopment": "0", "operatingExpenses": "19377000", "investmentIncomeNet": "None", "netInterestIncome": "None", "interestIncome": "None", "interestExpense": "4784000", "nonInterestIncome": "None", "otherNonOperatingIncome": "None", "depreciation": "None", "depreciationAndAmortization": "918000", "incomeBeforeTax": "3521000", "incomeTaxExpense": "1266000", "interestAndDebtExpense": "None", "netIncomeFromContinuingOperations": "0", "comprehensiveIncomeNetOfTax": "None", "ebit": "3521000", "ebitda": "4439000", "netIncome": "2255000"}, {"fiscalDateEnding": "2009-06-30", "reportedCurrency": "USD", "grossProfit": "23292000", "totalRevenue": "36428000", "costOfRevenue": "13136000", "costofGoodsAndServicesSold": "13136000", "operatingIncome": "3948000", "sellingGeneralAndAdministrative": "10069000", "researchAndDevelopment": "0", "operatingExpenses": "19344000", "investmentIncomeNet": "None", "netInterestIncome": "None", "interestIncome": "None", "interestExpense": "5286000", "nonInterestIncome": "None", "otherNonOperatingIncome": "None", "depreciation": "None", "depreciationAndAmortization": "910000", "incomeBeforeTax": "3948000", "incomeTaxExpense": "1436000", "interestAndDebtExpense": "None", "netIncomeFromContinuingOperations": "0", "comprehensiveIncomeNetOfTax": "None", "ebit": "3948000", "ebitda": "4858000", "netIncome": "2512000"}, {"fiscalDateEnding": "2009-03-31", "reportedCurrency": "USD", "grossProfit": "21813000", "totalRevenue": "35497000", "costOfRevenue": "13684000", "costofGoodsAndServicesSold": "13684000", "operatingIncome": "4612000", "sellingGeneralAndAdministrative": "9789000", "researchAndDevelopment": "0", "operatingExpenses": "17201000", "investmentIncomeNet": "None", "netInterestIncome": "None", "interestIncome": "None", "interestExpense": "5884000", "nonInterestIncome": "None", "otherNonOperatingIncome": "None", "depreciation": "None", "depreciationAndAmortization": "968000", "incomeBeforeTax": "4612000", "incomeTaxExpense": "1730000", "interestAndDebtExpense": "None", "netIncomeFromContinuingOperations": "0", "comprehensiveIncomeNetOfTax": "None", "ebit": "4612000", "ebitda": "5580000", "netIncome": "2882000"}, {"fiscalDateEnding": "2008-12-31", "reportedCurrency": "USD", "grossProfit": "23330000", "totalRevenue": "35844000", "costOfRevenue": "12514000", "costofGoodsAndServicesSold": "12514000", "operatingIncome": "6598000", "sellingGeneralAndAdministrative": "9556000", "researchAndDevelopment": "0", "operatingExpenses": "16732000", "investmentIncomeNet": "None", "netInterestIncome": "None", "interestIncome": "None", "interestExpense": "7064000", "nonInterestIncome": "None", "otherNonOperatingIncome": "None", "depreciation": "None", "depreciationAndAmortization": "1034000", "incomeBeforeTax": "6598000", "incomeTaxExpense": "2357000", "interestAndDebtExpense": "None", "netIncomeFromContinuingOperations": "0", "comprehensiveIncomeNetOfTax": "None", "ebit": "6598000", "ebitda": "7632000", "netIncome": "4241000"}, {"fiscalDateEnding": "2008-09-30", "reportedCurrency": "USD", "grossProfit": "26911000", "totalRevenue": "36763000", "costOfRevenue": "9852000", "costofGoodsAndServicesSold": "9852000", "operatingIncome": "10322000", "sellingGeneralAndAdministrative": "9431000", "researchAndDevelopment": "0", "operatingExpenses": "16589000", "investmentIncomeNet": "None", "netInterestIncome": "None", "interestIncome": "None", "interestExpense": "7252000", "nonInterestIncome": "None", "otherNonOperatingIncome": "None", "depreciation": "None", "depreciationAndAmortization": "1054000", "incomeBeforeTax": "10322000", "incomeTaxExpense": "4087000", "interestAndDebtExpense": "None", "netIncomeFromContinuingOperations": "0", "comprehensiveIncomeNetOfTax": "None", "ebit": "10322000", "ebitda": "11376000", "netIncome": "6235000"}, {"fiscalDateEnding": "2008-06-30", "reportedCurrency": "USD", "grossProfit": "21341000", "totalRevenue": "37612000", "costOfRevenue": "16271000", "costofGoodsAndServicesSold": "16271000", "operatingIncome": "3497000", "sellingGeneralAndAdministrative": "9645000", "researchAndDevelopment": "0", "operatingExpenses": "17844000", "investmentIncomeNet": "None", "netInterestIncome": "None", "interestIncome": "None", "interestExpense": "7471000", "nonInterestIncome": "None", "otherNonOperatingIncome": "None", "depreciation": "None", "depreciationAndAmortization": "1095000", "incomeBeforeTax": "3497000", "incomeTaxExpense": "1223000", "interestAndDebtExpense": "None", "netIncomeFromContinuingOperations": "0", "comprehensiveIncomeNetOfTax": "None", "ebit": "3497000", "ebitda": "4592000", "netIncome": "2274000"}, {"fiscalDateEnding": "2008-03-31", "reportedCurrency": "USD", "grossProfit": "24115000", "totalRevenue": "37980000", "costOfRevenue": "13865000", "costofGoodsAndServicesSold": "13865000", "operatingIncome": "6542000", "sellingGeneralAndAdministrative": "9480000", "researchAndDevelopment": "0", "operatingExpenses": "17573000", "investmentIncomeNet": "None", "netInterestIncome": "None", "interestIncome": "None", "interestExpense": "9765000", "nonInterestIncome": "None", "otherNonOperatingIncome": "None", "depreciation": "None", "depreciationAndAmortization": "1076000", "incomeBeforeTax": "6542000", "incomeTaxExpense": "2494000", "interestAndDebtExpense": "None", "netIncomeFromContinuingOperations": "0", "comprehensiveIncomeNetOfTax": "None", "ebit": "6542000", "ebitda": "7618000", "netIncome": "4048000"}, {"fiscalDateEnding": "2007-12-31", "reportedCurrency": "USD", "grossProfit": "27074000", "totalRevenue": "39293000", "costOfRevenue": "12219000", "costofGoodsAndServicesSold": "12219000", "operatingIncome": "9323000", "sellingGeneralAndAdministrative": "9730000", "researchAndDevelopment": "0", "operatingExpenses": "17751000", "investmentIncomeNet": "None", "netInterestIncome": "None", "interestIncome": "None", "interestExpense": "10869000", "nonInterestIncome": "None", "otherNonOperatingIncome": "None", "depreciation": "None", "depreciationAndAmortization": "1132000", "incomeBeforeTax": "9323000", "incomeTaxExpense": "3622000", "interestAndDebtExpense": "None", "netIncomeFromContinuingOperations": "0", "comprehensiveIncomeNetOfTax": "None", "ebit": "9323000", "ebitda": "10455000", "netIncome": "5701000"}, {"fiscalDateEnding": "2007-09-30", "reportedCurrency": "USD", "grossProfit": "27987000", "totalRevenue": "39289000", "costOfRevenue": "11302000", "costofGoodsAndServicesSold": "11302000", "operatingIncome": "11235000", "sellingGeneralAndAdministrative": "8975000", "researchAndDevelopment": "0", "operatingExpenses": "16752000", "investmentIncomeNet": "None", "netInterestIncome": "None", "interestIncome": "None", "interestExpense": "10602000", "nonInterestIncome": "None", "otherNonOperatingIncome": "None", "depreciation": "None", "depreciationAndAmortization": "1197000", "incomeBeforeTax": "11235000", "incomeTaxExpense": "4442000", "interestAndDebtExpense": "None", "netIncomeFromContinuingOperations": "0", "comprehensiveIncomeNetOfTax": "None", "ebit": "11235000", "ebitda": "12432000", "netIncome": "6793000"}, {"fiscalDateEnding": "2007-06-30", "reportedCurrency": "USD", "grossProfit": "28620000", "totalRevenue": "39015000", "costOfRevenue": "10395000", "costofGoodsAndServicesSold": "10395000", "operatingIncome": "11177000", "sellingGeneralAndAdministrative": "9619000", "researchAndDevelopment": "0", "operatingExpenses": "17443000", "investmentIncomeNet": "None", "netInterestIncome": "None", "interestIncome": "None", "interestExpense": "9895000", "nonInterestIncome": "None", "otherNonOperatingIncome": "None", "depreciation": "None", "depreciationAndAmortization": "1274000", "incomeBeforeTax": "11177000", "incomeTaxExpense": "4422000", "interestAndDebtExpense": "None", "netIncomeFromContinuingOperations": "0", "comprehensiveIncomeNetOfTax": "None", "ebit": "11177000", "ebitda": "12451000", "netIncome": "6755000"}, {"fiscalDateEnding": "2007-03-31", "reportedCurrency": "USD", "grossProfit": "27563000", "totalRevenue": "37261000", "costOfRevenue": "9698000", "costofGoodsAndServicesSold": "9698000", "operatingIncome": "10603000", "sellingGeneralAndAdministrative": "9742000", "researchAndDevelopment": "0", "operatingExpenses": "16960000", "investmentIncomeNet": "None", "netInterestIncome": "None", "interestIncome": "None", "interestExpense": "9216000", "nonInterestIncome": "None", "otherNonOperatingIncome": "None", "depreciation": "None", "depreciationAndAmortization": "1253000", "incomeBeforeTax": "10603000", "incomeTaxExpense": "4159000", "interestAndDebtExpense": "None", "netIncomeFromContinuingOperations": "0", "comprehensiveIncomeNetOfTax": "None", "ebit": "10603000", "ebitda": "11856000", "netIncome": "6444000"}, {"fiscalDateEnding": "2006-12-31", "reportedCurrency": "USD", "grossProfit": "28351000", "totalRevenue": "38172000", "costOfRevenue": "9821000", "costofGoodsAndServicesSold": "9821000", "operatingIncome": "11349000", "sellingGeneralAndAdministrative": "9405000", "researchAndDevelopment": "0", "operatingExpenses": "17002000", "investmentIncomeNet": "None", "netInterestIncome": "None", "interestIncome": "None", "interestExpense": "9821000", "nonInterestIncome": "None", "otherNonOperatingIncome": "None", "depreciation": "None", "depreciationAndAmortization": "1452000", "incomeBeforeTax": "11349000", "incomeTaxExpense": "4431000", "interestAndDebtExpense": "None", "netIncomeFromContinuingOperations": "0", "comprehensiveIncomeNetOfTax": "None", "ebit": "11349000", "ebitda": "12801000", "netIncome": "6918000"}, {"fiscalDateEnding": "2006-09-30", "reportedCurrency": "USD", "grossProfit": "28259000", "totalRevenue": "38070000", "costOfRevenue": "9811000", "costofGoodsAndServicesSold": "9811000", "operatingIncome": "11233000", "sellingGeneralAndAdministrative": "9276000", "researchAndDevelopment": "0", "operatingExpenses": "17026000", "investmentIncomeNet": "None", "netInterestIncome": "None", "interestIncome": "None", "interestExpense": "9576000", "nonInterestIncome": "None", "otherNonOperatingIncome": "None", "depreciation": "None", "depreciationAndAmortization": "1493000", "incomeBeforeTax": "11233000", "incomeTaxExpense": "4413000", "interestAndDebtExpense": "None", "netIncomeFromContinuingOperations": "0", "comprehensiveIncomeNetOfTax": "None", "ebit": "11233000", "ebitda": "12726000", "netIncome": "6820000"}, {"fiscalDateEnding": "2006-06-30", "reportedCurrency": "USD", "grossProfit": "27081000", "totalRevenue": "35910000", "costOfRevenue": "8829000", "costofGoodsAndServicesSold": "8829000", "operatingIncome": "10805000", "sellingGeneralAndAdministrative": "8618000", "researchAndDevelopment": "0", "operatingExpenses": "16276000", "investmentIncomeNet": "None", "netInterestIncome": "None", "interestIncome": "None", "interestExpense": "8275000", "nonInterestIncome": "None", "otherNonOperatingIncome": "None", "depreciation": "None", "depreciationAndAmortization": "1489000", "incomeBeforeTax": "10805000", "incomeTaxExpense": "4248000", "interestAndDebtExpense": "None", "netIncomeFromContinuingOperations": "0", "comprehensiveIncomeNetOfTax": "None", "ebit": "10805000", "ebitda": "12294000", "netIncome": "6557000"}, {"fiscalDateEnding": "2006-03-31", "reportedCurrency": "USD", "grossProfit": "27153000", "totalRevenue": "34426000", "costOfRevenue": "7273000", "costofGoodsAndServicesSold": "7273000", "operatingIncome": "10731000", "sellingGeneralAndAdministrative": "9156000", "researchAndDevelopment": "0", "operatingExpenses": "16422000", "investmentIncomeNet": "None", "netInterestIncome": "None", "interestIncome": "None", "interestExpense": "6773000", "nonInterestIncome": "None", "otherNonOperatingIncome": "None", "depreciation": "None", "depreciationAndAmortization": "1569000", "incomeBeforeTax": "10731000", "incomeTaxExpense": "4196000", "interestAndDebtExpense": "None", "netIncomeFromContinuingOperations": "0", "comprehensiveIncomeNetOfTax": "None", "ebit": "10731000", "ebitda": "12300000", "netIncome": "6535000"}]}}